{
  "HEADER_DATA": [
    {
      "COMP_CODE": "1000",
      "DOC_NO": "0900000000",
      "FISC_YEAR": "2019",
      "DOC_TYPE": "KZ",
      "DOC_DATE": "20191001",
      "POST_DATE": "20191003",
      "ENTRY_DATE": "20191003",
      "REFERENCE": "",
      "REV_WITH": "",
      "REV_YEAR": "0000",
      "DOC_HDR_TXT": "",
      "CURRENCY": "IDR",
      "EXCH_RATE": "                                                                                                                                                                                                                                                       0.00000",
      "REFERENCE_KEY": "090000000010002019",
      "PMT_IND": "",
      "TRANS_TYPE": "",
      "SPREAD_VAL": ""
    },
    {
      "COMP_CODE": "1000",
      "DOC_NO": "0900000001",
      "FISC_YEAR": "2019",
      "DOC_TYPE": "KZ",
      "DOC_DATE": "20191001",
      "POST_DATE": "20191003",
      "ENTRY_DATE": "20191003",
      "REFERENCE": "",
      "REV_WITH": "",
      "REV_YEAR": "0000",
      "DOC_HDR_TXT": "",
      "CURRENCY": "IDR",
      "EXCH_RATE": "                                                                                                                                                                                                                                                       0.00000",
      "REFERENCE_KEY": "090000000110002019",
      "PMT_IND": "",
      "TRANS_TYPE": "",
      "SPREAD_VAL": ""
    },
    {
      "COMP_CODE": "1000",
      "DOC_NO": "0900000002",
      "FISC_YEAR": "2019",
      "DOC_TYPE": "KZ",
      "DOC_DATE": "20191001",
      "POST_DATE": "20191003",
      "ENTRY_DATE": "20191003",
      "REFERENCE": "",
      "REV_WITH": "1000000196",
      "REV_YEAR": "2019",
      "DOC_HDR_TXT": "",
      "CURRENCY": "IDR",
      "EXCH_RATE": "                                                                                                                                                                                                                                                       0.00000",
      "REFERENCE_KEY": "090000000210002019",
      "PMT_IND": "",
      "TRANS_TYPE": "",
      "SPREAD_VAL": ""
    },
    {
      "COMP_CODE": "1000",
      "DOC_NO": "0900000003",
      "FISC_YEAR": "2019",
      "DOC_TYPE": "KZ",
      "DOC_DATE": "20191001",
      "POST_DATE": "20191004",
      "ENTRY_DATE": "20191003",
      "REFERENCE": "",
      "REV_WITH": "1000000195",
      "REV_YEAR": "2019",
      "DOC_HDR_TXT": "",
      "CURRENCY": "IDR",
      "EXCH_RATE": "                                                                                                                                                                                                                                                       0.00000",
      "REFERENCE_KEY": "090000000310002019",
      "PMT_IND": "",
      "TRANS_TYPE": "",
      "SPREAD_VAL": ""
    },
    {
      "COMP_CODE": "1000",
      "DOC_NO": "3200000003",
      "FISC_YEAR": "2019",
      "DOC_TYPE": "YM",
      "DOC_DATE": "20191001",
      "POST_DATE": "20191003",
      "ENTRY_DATE": "20191003",
      "REFERENCE": "",
      "REV_WITH": "2100000001",
      "REV_YEAR": "2019",
      "DOC_HDR_TXT": "",
      "CURRENCY": "IDR",
      "EXCH_RATE": "                                                                                                                                                                                                                                                       0.00000",
      "REFERENCE_KEY": "320000000310002019",
      "PMT_IND": "",
      "TRANS_TYPE": "",
      "SPREAD_VAL": ""
    }
  ],
  "ITEM_DATA": [
    {
      "COMP_CODE": "1000",
      "DOC_NO": "0900000000",
      "FISC_YEAR": "2019",
      "LINE_ITEM": "001",
      "ACCT_TYPE": "S - G/L Account",
      "SPEC_GL": "",
      "BUS_AREA": "1001",
      "TPBA": "",
      "DR_CR_IND": "H",
      "AMT_LC": "                                                                                                                                                                                                                                                      94000.00",
      "AMT_TC": "                                                                                                                                                                                                                                                      94000.00",
      "AMT_WITH_BASE_TC": "                                                                                                                                                                                                                                                          0.00",
      "AMT_WITH_TC": "                                                                                                                                                                                                                                                          0.00",
      "ASSIGNMENT": "investasi-jasa",
      "ITEM_TEXT": "Payment Unit",
      "COST_CTR": "",
      "GL_ACCT": "1202012662",
      "CUSTOMER": "",
      "VENDOR": "",
      "BASE_DATE": "00000000",
      "TERM_PMT": "",
      "DUE_ON": "00000000",
      "PMT_BLOCK": "",
      "HOUSE_BANK": "",
      "PRTNR_BANK_TYPE": "",
      "PO_NUM": "",
      "PO_ITEM": "00000",
      "REF_KEY1": "",
      "REF_KEY2": "",
      "REF_KEY3": "",
      "INT_ORDER": "",
      "WBS_NUM": "00000000",
      "CASH_CODE": "2.7"
    },
    {
      "COMP_CODE": "1000",
      "DOC_NO": "0900000000",
      "FISC_YEAR": "2019",
      "LINE_ITEM": "002",
      "ACCT_TYPE": "S - G/L Account",
      "SPEC_GL": "",
      "BUS_AREA": "1001",
      "TPBA": "4A01",
      "DR_CR_IND": "S",
      "AMT_LC": "                                                                                                                                                                                                                                                      94000.00",
      "AMT_TC": "                                                                                                                                                                                                                                                      94000.00",
      "AMT_WITH_BASE_TC": "                                                                                                                                                                                                                                                          0.00",
      "AMT_WITH_TC": "                                                                                                                                                                                                                                                          0.00",
      "ASSIGNMENT": "investasi-jasa",
      "ITEM_TEXT": "Payment Unit",
      "COST_CTR": "",
      "GL_ACCT": "8101100000",
      "CUSTOMER": "",
      "VENDOR": "",
      "BASE_DATE": "00000000",
      "TERM_PMT": "",
      "DUE_ON": "00000000",
      "PMT_BLOCK": "",
      "HOUSE_BANK": "",
      "PRTNR_BANK_TYPE": "",
      "PO_NUM": "",
      "PO_ITEM": "00000",
      "REF_KEY1": "",
      "REF_KEY2": "",
      "REF_KEY3": "",
      "INT_ORDER": "",
      "WBS_NUM": "00000000",
      "CASH_CODE": ""
    },
    {
      "COMP_CODE": "1000",
      "DOC_NO": "0900000001",
      "FISC_YEAR": "2019",
      "LINE_ITEM": "001",
      "ACCT_TYPE": "S - G/L Account",
      "SPEC_GL": "",
      "BUS_AREA": "1001",
      "TPBA": "",
      "DR_CR_IND": "H",
      "AMT_LC": "                                                                                                                                                                                                                                                      80000.00",
      "AMT_TC": "                                                                                                                                                                                                                                                      80000.00",
      "AMT_WITH_BASE_TC": "                                                                                                                                                                                                                                                          0.00",
      "AMT_WITH_TC": "                                                                                                                                                                                                                                                          0.00",
      "ASSIGNMENT": "20191003",
      "ITEM_TEXT": "",
      "COST_CTR": "",
      "GL_ACCT": "1202012662",
      "CUSTOMER": "",
      "VENDOR": "",
      "BASE_DATE": "00000000",
      "TERM_PMT": "",
      "DUE_ON": "00000000",
      "PMT_BLOCK": "",
      "HOUSE_BANK": "",
      "PRTNR_BANK_TYPE": "",
      "PO_NUM": "",
      "PO_ITEM": "00000",
      "REF_KEY1": "",
      "REF_KEY2": "",
      "REF_KEY3": "",
      "INT_ORDER": "",
      "WBS_NUM": "00000000",
      "CASH_CODE": "2.3"
    },
    {
      "COMP_CODE": "1000",
      "DOC_NO": "0900000001",
      "FISC_YEAR": "2019",
      "LINE_ITEM": "002",
      "ACCT_TYPE": "K - Vendor",
      "SPEC_GL": "",
      "BUS_AREA": "1001",
      "TPBA": "",
      "DR_CR_IND": "S",
      "AMT_LC": "                                                                                                                                                                                                                                                      80000.00",
      "AMT_TC": "                                                                                                                                                                                                                                                      80000.00",
      "AMT_WITH_BASE_TC": "                                                                                                                                                                                                                                                          0.00",
      "AMT_WITH_TC": "                                                                                                                                                                                                                                                          0.00",
      "ASSIGNMENT": "",
      "ITEM_TEXT": "",
      "COST_CTR": "",
      "GL_ACCT": "3109400000",
      "CUSTOMER": "",
      "VENDOR": "0500005798",
      "BASE_DATE": "20191001",
      "TERM_PMT": "",
      "DUE_ON": "20191001",
      "PMT_BLOCK": "",
      "HOUSE_BANK": "",
      "PRTNR_BANK_TYPE": "",
      "PO_NUM": "",
      "PO_ITEM": "00000",
      "REF_KEY1": "",
      "REF_KEY2": "",
      "REF_KEY3": "",
      "INT_ORDER": "",
      "WBS_NUM": "00000000",
      "CASH_CODE": ""
    },
    {
      "COMP_CODE": "1000",
      "DOC_NO": "0900000002",
      "FISC_YEAR": "2019",
      "LINE_ITEM": "001",
      "ACCT_TYPE": "S - G/L Account",
      "SPEC_GL": "",
      "BUS_AREA": "1001",
      "TPBA": "",
      "DR_CR_IND": "H",
      "AMT_LC": "                                                                                                                                                                                                                                                    4250000.00",
      "AMT_TC": "                                                                                                                                                                                                                                                    4250000.00",
      "AMT_WITH_BASE_TC": "                                                                                                                                                                                                                                                          0.00",
      "AMT_WITH_TC": "                                                                                                                                                                                                                                                          0.00",
      "ASSIGNMENT": "20191003",
      "ITEM_TEXT": "Medical Reimbursement Vendor - Residual 1",
      "COST_CTR": "",
      "GL_ACCT": "1202012662",
      "CUSTOMER": "",
      "VENDOR": "",
      "BASE_DATE": "00000000",
      "TERM_PMT": "",
      "DUE_ON": "00000000",
      "PMT_BLOCK": "",
      "HOUSE_BANK": "",
      "PRTNR_BANK_TYPE": "",
      "PO_NUM": "",
      "PO_ITEM": "00000",
      "REF_KEY1": "",
      "REF_KEY2": "",
      "REF_KEY3": "",
      "INT_ORDER": "",
      "WBS_NUM": "00000000",
      "CASH_CODE": "1.7.5.2.10"
    },
    {
      "COMP_CODE": "1000",
      "DOC_NO": "0900000002",
      "FISC_YEAR": "2019",
      "LINE_ITEM": "002",
      "ACCT_TYPE": "K - Vendor",
      "SPEC_GL": "",
      "BUS_AREA": "1001",
      "TPBA": "",
      "DR_CR_IND": "H",
      "AMT_LC": "                                                                                                                                                                                                                                                   10000000.00",
      "AMT_TC": "                                                                                                                                                                                                                                                   10000000.00",
      "AMT_WITH_BASE_TC": "                                                                                                                                                                                                                                                          0.00",
      "AMT_WITH_TC": "                                                                                                                                                                                                                                                          0.00",
      "ASSIGNMENT": "",
      "ITEM_TEXT": "Medical Reimbursement Vendor - Residual 1",
      "COST_CTR": "",
      "GL_ACCT": "3202001000",
      "CUSTOMER": "",
      "VENDOR": "0500005466",
      "BASE_DATE": "20191003",
      "TERM_PMT": "ZP03",
      "DUE_ON": "20191017",
      "PMT_BLOCK": "",
      "HOUSE_BANK": "",
      "PRTNR_BANK_TYPE": "",
      "PO_NUM": "",
      "PO_ITEM": "00000",
      "REF_KEY1": "",
      "REF_KEY2": "",
      "REF_KEY3": "",
      "INT_ORDER": "",
      "WBS_NUM": "00000000",
      "CASH_CODE": ""
    },
    {
      "COMP_CODE": "1000",
      "DOC_NO": "0900000002",
      "FISC_YEAR": "2019",
      "LINE_ITEM": "003",
      "ACCT_TYPE": "K - Vendor",
      "SPEC_GL": "",
      "BUS_AREA": "1001",
      "TPBA": "",
      "DR_CR_IND": "S",
      "AMT_LC": "                                                                                                                                                                                                                                                   15000000.00",
      "AMT_TC": "                                                                                                                                                                                                                                                   15000000.00",
      "AMT_WITH_BASE_TC": "                                                                                                                                                                                                                                                     150000.00",
      "AMT_WITH_TC": "                                                                                                                                                                                                                                                          0.00",
      "ASSIGNMENT": "",
      "ITEM_TEXT": "",
      "COST_CTR": "",
      "GL_ACCT": "3202001000",
      "CUSTOMER": "",
      "VENDOR": "0500005466",
      "BASE_DATE": "20191001",
      "TERM_PMT": "",
      "DUE_ON": "20191001",
      "PMT_BLOCK": "",
      "HOUSE_BANK": "",
      "PRTNR_BANK_TYPE": "",
      "PO_NUM": "",
      "PO_ITEM": "00000",
      "REF_KEY1": "",
      "REF_KEY2": "",
      "REF_KEY3": "",
      "INT_ORDER": "",
      "WBS_NUM": "00000000",
      "CASH_CODE": ""
    },
    {
      "COMP_CODE": "1000",
      "DOC_NO": "0900000002",
      "FISC_YEAR": "2019",
      "LINE_ITEM": "004",
      "ACCT_TYPE": "S - G/L Account",
      "SPEC_GL": "",
      "BUS_AREA": "1001",
      "TPBA": "",
      "DR_CR_IND": "H",
      "AMT_LC": "                                                                                                                                                                                                                                                     750000.00",
      "AMT_TC": "                                                                                                                                                                                                                                                     750000.00",
      "AMT_WITH_BASE_TC": "                                                                                                                                                                                                                                                          0.00",
      "AMT_WITH_TC": "                                                                                                                                                                                                                                                          0.00",
      "ASSIGNMENT": "20191003",
      "ITEM_TEXT": "",
      "COST_CTR": "",
      "GL_ACCT": "3203000200",
      "CUSTOMER": "",
      "VENDOR": "",
      "BASE_DATE": "00000000",
      "TERM_PMT": "",
      "DUE_ON": "00000000",
      "PMT_BLOCK": "",
      "HOUSE_BANK": "",
      "PRTNR_BANK_TYPE": "",
      "PO_NUM": "",
      "PO_ITEM": "00000",
      "REF_KEY1": "",
      "REF_KEY2": "",
      "REF_KEY3": "",
      "INT_ORDER": "",
      "WBS_NUM": "00000000",
      "CASH_CODE": ""
    },
    {
      "COMP_CODE": "1000",
      "DOC_NO": "0900000003",
      "FISC_YEAR": "2019",
      "LINE_ITEM": "001",
      "ACCT_TYPE": "S - G/L Account",
      "SPEC_GL": "",
      "BUS_AREA": "1001",
      "TPBA": "",
      "DR_CR_IND": "H",
      "AMT_LC": "                                                                                                                                                                                                                                                    8500000.00",
      "AMT_TC": "                                                                                                                                                                                                                                                    8500000.00",
      "AMT_WITH_BASE_TC": "                                                                                                                                                                                                                                                          0.00",
      "AMT_WITH_TC": "                                                                                                                                                                                                                                                          0.00",
      "ASSIGNMENT": "20191003",
      "ITEM_TEXT": "Medical Reimbursement Vendor - Residual 2",
      "COST_CTR": "",
      "GL_ACCT": "1202012662",
      "CUSTOMER": "",
      "VENDOR": "",
      "BASE_DATE": "00000000",
      "TERM_PMT": "",
      "DUE_ON": "00000000",
      "PMT_BLOCK": "",
      "HOUSE_BANK": "",
      "PRTNR_BANK_TYPE": "",
      "PO_NUM": "",
      "PO_ITEM": "00000",
      "REF_KEY1": "",
      "REF_KEY2": "",
      "REF_KEY3": "",
      "INT_ORDER": "",
      "WBS_NUM": "00000000",
      "CASH_CODE": "1.7.5.2.10"
    },
    {
      "COMP_CODE": "1000",
      "DOC_NO": "0900000003",
      "FISC_YEAR": "2019",
      "LINE_ITEM": "002",
      "ACCT_TYPE": "K - Vendor",
      "SPEC_GL": "",
      "BUS_AREA": "1001",
      "TPBA": "",
      "DR_CR_IND": "S",
      "AMT_LC": "                                                                                                                                                                                                                                                   10000000.00",
      "AMT_TC": "                                                                                                                                                                                                                                                   10000000.00",
      "AMT_WITH_BASE_TC": "                                                                                                                                                                                                                                                          0.00",
      "AMT_WITH_TC": "                                                                                                                                                                                                                                                          0.00",
      "ASSIGNMENT": "",
      "ITEM_TEXT": "",
      "COST_CTR": "",
      "GL_ACCT": "3202001000",
      "CUSTOMER": "",
      "VENDOR": "0500005466",
      "BASE_DATE": "20191001",
      "TERM_PMT": "",
      "DUE_ON": "20191001",
      "PMT_BLOCK": "",
      "HOUSE_BANK": "",
      "PRTNR_BANK_TYPE": "",
      "PO_NUM": "",
      "PO_ITEM": "00000",
      "REF_KEY1": "",
      "REF_KEY2": "",
      "REF_KEY3": "",
      "INT_ORDER": "",
      "WBS_NUM": "00000000",
      "CASH_CODE": ""
    },
    {
      "COMP_CODE": "1000",
      "DOC_NO": "0900000003",
      "FISC_YEAR": "2019",
      "LINE_ITEM": "003",
      "ACCT_TYPE": "S - G/L Account",
      "SPEC_GL": "",
      "BUS_AREA": "1001",
      "TPBA": "",
      "DR_CR_IND": "H",
      "AMT_LC": "                                                                                                                                                                                                                                                    1500000.00",
      "AMT_TC": "                                                                                                                                                                                                                                                    1500000.00",
      "AMT_WITH_BASE_TC": "                                                                                                                                                                                                                                                          0.00",
      "AMT_WITH_TC": "                                                                                                                                                                                                                                                          0.00",
      "ASSIGNMENT": "20191004",
      "ITEM_TEXT": "",
      "COST_CTR": "",
      "GL_ACCT": "3203000200",
      "CUSTOMER": "",
      "VENDOR": "",
      "BASE_DATE": "00000000",
      "TERM_PMT": "",
      "DUE_ON": "00000000",
      "PMT_BLOCK": "",
      "HOUSE_BANK": "",
      "PRTNR_BANK_TYPE": "",
      "PO_NUM": "",
      "PO_ITEM": "00000",
      "REF_KEY1": "",
      "REF_KEY2": "",
      "REF_KEY3": "",
      "INT_ORDER": "",
      "WBS_NUM": "00000000",
      "CASH_CODE": ""
    },
    {
      "COMP_CODE": "1000",
      "DOC_NO": "3200000003",
      "FISC_YEAR": "2019",
      "LINE_ITEM": "001",
      "ACCT_TYPE": "S - G/L Account",
      "SPEC_GL": "",
      "BUS_AREA": "1001",
      "TPBA": "",
      "DR_CR_IND": "H",
      "AMT_LC": "                                                                                                                                                                                                                                                    6300000.00",
      "AMT_TC": "                                                                                                                                                                                                                                                    6300000.00",
      "AMT_WITH_BASE_TC": "                                                                                                                                                                                                                                                          0.00",
      "AMT_WITH_TC": "                                                                                                                                                                                                                                                          0.00",
      "ASSIGNMENT": "20191003",
      "ITEM_TEXT": "Medical Reimbursement Employee",
      "COST_CTR": "",
      "GL_ACCT": "1202012662",
      "CUSTOMER": "",
      "VENDOR": "",
      "BASE_DATE": "00000000",
      "TERM_PMT": "",
      "DUE_ON": "00000000",
      "PMT_BLOCK": "",
      "HOUSE_BANK": "",
      "PRTNR_BANK_TYPE": "",
      "PO_NUM": "",
      "PO_ITEM": "00000",
      "REF_KEY1": "",
      "REF_KEY2": "",
      "REF_KEY3": "",
      "INT_ORDER": "",
      "WBS_NUM": "00000000",
      "CASH_CODE": "1.7.5.2.10"
    },
    {
      "COMP_CODE": "1000",
      "DOC_NO": "3200000003",
      "FISC_YEAR": "2019",
      "LINE_ITEM": "002",
      "ACCT_TYPE": "D - Customers",
      "SPEC_GL": "K",
      "BUS_AREA": "1001",
      "TPBA": "",
      "DR_CR_IND": "S",
      "AMT_LC": "                                                                                                                                                                                                                                                    6300000.00",
      "AMT_TC": "                                                                                                                                                                                                                                                    6300000.00",
      "AMT_WITH_BASE_TC": "                                                                                                                                                                                                                                                          0.00",
      "AMT_WITH_TC": "                                                                                                                                                                                                                                                          0.00",
      "ASSIGNMENT": "",
      "ITEM_TEXT": "",
      "COST_CTR": "",
      "GL_ACCT": "3202001500",
      "CUSTOMER": "0295140008",
      "VENDOR": "",
      "BASE_DATE": "20191001",
      "TERM_PMT": "",
      "DUE_ON": "20191001",
      "PMT_BLOCK": "",
      "HOUSE_BANK": "",
      "PRTNR_BANK_TYPE": "",
      "PO_NUM": "",
      "PO_ITEM": "00000",
      "REF_KEY1": "",
      "REF_KEY2": "",
      "REF_KEY3": "",
      "INT_ORDER": "",
      "WBS_NUM": "00000000",
      "CASH_CODE": ""
    }
  ],
  "PAYMENT_INVOICE_MAP": [
    {
      "PMT_COMP_CODE": "1000",
      "PMT_DOC_NO": "0900000000",
      "PMT_FISC_YEAR": "2019",
      "INV_COMP_CODE": "4A00",
      "INV_DOC_NO": "7100000069",
      "INV_FISC_YEAR": "2015"
    }
  ]
}